Metadata-Version: 2.1
Name: chat-shell
Version: 0.1.0
Summary: An intelligent shell with AI chat capabilities
Home-page: https://github.com/l1905/smart_shell
Author: litongxue
Author-email: litonglitong@hotmail.com
Classifier: Programming Language :: Python :: 3
Classifier: License :: OSI Approved :: MIT License
Classifier: Operating System :: OS Independent
Requires-Python: >=3.7
Requires-Dist: prompt_toolkit==3.0.48
Requires-Dist: Pygments==2.18.0
Requires-Dist: Requests==2.32.3
Requires-Dist: tenacity==9.0.0
